simple_mistral/__init__.py
simple_mistral/client.py
simple_mistral-0.1.2.dist-info/licenses/LICENSE
tests/__init__.py
tests/conftest.py
tests/test_client.py
tests/testdata.py
simple_mistral-0.1.2.dist-info/METADATA
simple_mistral-0.1.2.dist-info/WHEEL
simple_mistral-0.1.2.dist-info/top_level.txt
simple_mistral-0.1.2.dist-info/RECORD
