Metadata-Version: 2.4
Name: simple-mistral
Version: 0.1.2
Summary: A simple async and sync Mistral API client
Home-page: https://github.com/alaex777/simple-mistral
Author: Alexander Balashov
Author-email: alaex777@gmail.com
Classifier: Programming Language :: Python :: 3
Classifier: License :: OSI Approved :: MIT License
Classifier: Operating System :: OS Independent
Requires-Python: >=3.9
License-File: LICENSE
Requires-Dist: requests>=2.31.0
Requires-Dist: aiohttp>=3.9.0
Dynamic: author
Dynamic: author-email
Dynamic: classifier
Dynamic: description
Dynamic: description-content-type
Dynamic: home-page
Dynamic: license-file
Dynamic: requires-dist
Dynamic: requires-python
Dynamic: summary
